pytest_catchlog.py
pytest_catchlog-1.2.2.dist-info/top_level.txt
pytest_catchlog-1.2.2.dist-info/entry_points.txt
pytest_catchlog-1.2.2.dist-info/METADATA
pytest_catchlog-1.2.2.dist-info/DESCRIPTION.rst
pytest_catchlog-1.2.2.dist-info/metadata.json
pytest_catchlog-1.2.2.dist-info/WHEEL
pytest_catchlog-1.2.2.dist-info/RECORD
