Metadata-Version: 1.1
Name: pytest-catchlog
Version: 1.2.2
Summary: py.test plugin to catch log messages. This is a fork of pytest-capturelog.
Home-page: https://github.com/eisensheng/pytest-catchlog
Author: Arthur Skowronek (Fork Author)
Author-email: eisensheng@mailbox.org
License: MIT License
Keywords: py.test pytest logging
Platform: UNKNOWN
Classifier: Development Status :: 4 - Beta
Classifier: Intended Audience :: Developers
Classifier: License :: OSI Approved :: MIT License
Classifier: Operating System :: OS Independent
Classifier: Programming Language :: Python
Classifier: Programming Language :: Python :: 2.6
Classifier: Programming Language :: Python :: 2.7
Classifier: Programming Language :: Python :: 3
Classifier: Programming Language :: Python :: 3.2
Classifier: Programming Language :: Python :: 3.3
Classifier: Programming Language :: Python :: 3.4
Classifier: Programming Language :: Python :: 3.5
Classifier: Programming Language :: Python :: Implementation :: CPython
Classifier: Programming Language :: Python :: Implementation :: PyPy
Classifier: Topic :: Software Development :: Testing
